setup.cfg
setup.py
bckmodels/__init__.py
bckmodels/models.py
mingus/__init__.py
mingus/constants.py
mingus/exceptions.py
mingus/factories.py
mingus/handler.py
mingus/register.py
mingus/resources.py
mingus/resources_restless.py
mingus/serializers.py
mingus/server.py
mingus/service/__init__.py
mingus/service/models.py
mingus/service/resource.py
mingus_rest_framework.egg-info/PKG-INFO
mingus_rest_framework.egg-info/SOURCES.txt
mingus_rest_framework.egg-info/dependency_links.txt
mingus_rest_framework.egg-info/requires.txt
mingus_rest_framework.egg-info/top_level.txt
services/__init__.py
services/models.py
services/resource.py