Metadata-Version: 1.1
Name: mingus-rest-framework
Version: 0.1
Summary: Mingus is a small and flexible  restful framework on top of Tornado. It provides a simpler way to create RESTful API's.
Home-page: https://github.com/tgonzales/mingus
Author: github.com/tgonzales
Author-email: dev.cleiton.couto@gmail.com
License: MIT
Download-URL: https://github.com/tgonzales/mingus/archive/v0.1.tar.gz
Keywords: restful,rest,api,tornado,motor
Platform: UNKNOWN
Classifier: Development Status :: 3 - Alpha
Classifier: Intended Audience :: Developers
Classifier: License :: OSI Approved :: MIT License
Classifier: Natural Language :: English
Classifier: Operating System :: POSIX :: Linux
Classifier: Programming Language :: Python :: 3.4
